motu_server/__init__.py
motu_server/datastore.py
motu_server/server.py
motu_server/zeroconf_registration.py
motu_server-0.1.15.dist-info/LICENSE
motu_server-0.1.15.dist-info/METADATA
motu_server-0.1.15.dist-info/WHEEL
motu_server-0.1.15.dist-info/top_level.txt
motu_server-0.1.15.dist-info/RECORD
