Metadata-Version: 2.1
Name: motu_server
Version: 0.1.15
Summary: A tornado web server emulating a MOTU AVB interface's datastore API. Enables development of tools to read and manipulate the datastore without requiring an active interface.
Author-email: Christopher Johnston <christopher_johnston@me.com>
License: MIT License
Project-URL: Homepage, https://github.com/ChristopherJohnston/motu_server
Keywords: motu,avb,development
Classifier: License :: OSI Approved :: MIT License
Classifier: Programming Language :: Python
Classifier: Programming Language :: Python :: 3
Requires-Python: >=3.11
License-File: LICENSE
Requires-Dist: tornado
Requires-Dist: aiohttp
Requires-Dist: zeroconf
